notifications_rest/__init__.py
notifications_rest/apps.py
notifications_rest/serializers.py
notifications_rest/urls.py
notifications_rest/views.py
notifications_rest/migrations/__init__.py
notifications_rest/tests/__init__.py
notifications_rest/tests/test_views.py
test_project/__init__.py
test_project/settings.py
test_project/urls.py
test_project/wsgi.py
django_notifications_rest-1.0.2.dist-info/METADATA
django_notifications_rest-1.0.2.dist-info/WHEEL
django_notifications_rest-1.0.2.dist-info/top_level.txt
django_notifications_rest-1.0.2.dist-info/RECORD
